streamlit_custom_bar/__init__.py
streamlit_custom_bar/frontend/build/asset-manifest.json
streamlit_custom_bar/frontend/build/bootstrap.min.css
streamlit_custom_bar/frontend/build/index.html
streamlit_custom_bar/frontend/build/static/css/main.b5be1b03.css
streamlit_custom_bar/frontend/build/static/css/main.b5be1b03.css.map
streamlit_custom_bar/frontend/build/static/js/main.531da7b9.js
streamlit_custom_bar/frontend/build/static/js/main.531da7b9.js.LICENSE.txt
streamlit_custom_bar/frontend/build/static/js/main.531da7b9.js.map
streamlit_nivo_custom_bar-0.0.12.dist-info/LICENSE
streamlit_nivo_custom_bar-0.0.12.dist-info/METADATA
streamlit_nivo_custom_bar-0.0.12.dist-info/WHEEL
streamlit_nivo_custom_bar-0.0.12.dist-info/top_level.txt
streamlit_nivo_custom_bar-0.0.12.dist-info/RECORD
