Metadata-Version: 2.1
Name: streamlit-nivo-custom-bar
Version: 0.0.12
Home-page: 
Author: 
Author-email: 
Requires-Python: >=3.7
License-File: LICENSE
Requires-Dist: streamlit (>=0.63)
